Data_Cdvst/Files_Cdvst.py
Data_Cdvst/__init__.py
Data_Cdvst-1.4.dist-info/METADATA
Data_Cdvst-1.4.dist-info/WHEEL
Data_Cdvst-1.4.dist-info/top_level.txt
Data_Cdvst-1.4.dist-info/RECORD
