Metadata-Version: 2.1
Name: Data-Cdvst
Version: 1.4
Summary: Eine Python-Bibliothek zur einfachen Daten mangagment datenbanken undmehr und -aufnahme.
Home-page: https://now4free.de/python/module/Data_Cdvst
Author: Philipp Juen
Author-email: support@now4free.de
License: MIT
Project-URL: Source, https://github.com/philippjuen/Audio_Cdvst
Keywords: data,db,database,data handling,data saving,data sorting
Classifier: Development Status :: 3 - Alpha
Classifier: Intended Audience :: Developers
Classifier: License :: OSI Approved :: MIT License
Classifier: Programming Language :: Python :: 3
Classifier: Programming Language :: Python :: 3.6
Classifier: Programming Language :: Python :: 3.7
Classifier: Programming Language :: Python :: 3.8
Classifier: Programming Language :: Python :: 3.9
